qip2/__init__.py
qip2-1.6.0.0.data/data/lib/site-packages/qip2/boost_numpy36-vc142-mt-x64-1_72.dll
qip2-1.6.0.0.data/data/lib/site-packages/qip2/boost_python36-vc142-mt-x64-1_72.dll
qip2-1.6.0.0.data/data/lib/site-packages/qip2/c.dll
qip2-1.6.0.0.data/data/lib/site-packages/qip2/qip.pyd
qip2-1.6.0.0.dist-info/LICENSE
qip2-1.6.0.0.dist-info/METADATA
qip2-1.6.0.0.dist-info/WHEEL
qip2-1.6.0.0.dist-info/top_level.txt
qip2-1.6.0.0.dist-info/RECORD
