Metadata-Version: 2.1
Name: qip2
Version: 1.6.0.0
Summary: Integrate kdb+ into python
Home-page: https://bitbucket.org/kuentang/pykdb/src/master
Author: Kim Kuen Tang
Author-email: kimktang@gmail.com
License: UNKNOWN
Platform: UNKNOWN
Classifier: Programming Language :: Python :: 3
Classifier: License :: OSI Approved :: MIT License
Classifier: Operating System :: Microsoft :: Windows :: Windows 10
